zone/BaseNodeData.py
zone/__init__.py
zone/application.py
zone/version.py
zone/IDL/__init__.py
zone/IDL/thrift/__init__.py
zone/IDL/thrift/CanParserNode/__init__.py
zone/IDL/thrift/CanParserNode/canParserNode.py
zone/IDL/thrift/CanParserNode/constants.py
zone/IDL/thrift/CanParserNode/ttypes.py
zone/IDL/thrift/CanStackNode/__init__.py
zone/IDL/thrift/CanStackNode/canStackNode.py
zone/IDL/thrift/CanStackNode/constants.py
zone/IDL/thrift/CanStackNode/ttypes.py
zone/IDL/thrift/CommonNode/__init__.py
zone/IDL/thrift/CommonNode/constants.py
zone/IDL/thrift/CommonNode/ttypes.py
zone/IDL/thrift/ConfigNode/__init__.py
zone/IDL/thrift/ConfigNode/configNode.py
zone/IDL/thrift/ConfigNode/constants.py
zone/IDL/thrift/ConfigNode/ttypes.py
zone/IDL/thrift/LinParserNode/__init__.py
zone/IDL/thrift/LinParserNode/constants.py
zone/IDL/thrift/LinParserNode/linParserNode.py
zone/IDL/thrift/LinParserNode/ttypes.py
zone/IDL/thrift/LinStackNode/__init__.py
zone/IDL/thrift/LinStackNode/constants.py
zone/IDL/thrift/LinStackNode/linStackNode.py
zone/IDL/thrift/LinStackNode/ttypes.py
zone/IDL/thrift/SomeIpNode/__init__.py
zone/IDL/thrift/SomeIpNode/constants.py
zone/IDL/thrift/SomeIpNode/someIpNode.py
zone/IDL/thrift/SomeIpNode/ttypes.py
zone/clients/__init__.py
zone/clients/CanParserClient/CanParserClient.py
zone/clients/CanParserClient/__init__.py
zone/clients/CanStackClient/CanStackClient.py
zone/clients/CanStackClient/__init__.py
zone/clients/ConfigClient/ConfigClient.py
zone/clients/ConfigClient/__init__.py
zone/clients/LinParserClient/LinParserClient.py
zone/clients/LinParserClient/__init__.py
zone/clients/LinStackClient/LinStackClient.py
zone/clients/LinStackClient/__init__.py
zone/dsc/__init__.py
zone/dsc/base.py
zone/etc/zonemaster_config.yaml
zone/utils/__init__.py
zone/utils/application.py
zone/utils/config.py
zone/utils/decorator.py
zone/utils/dsx.py
zone/utils/snippets.py
zone_hub-0.1.0.dev5.dist-info/METADATA
zone_hub-0.1.0.dev5.dist-info/WHEEL
zone_hub-0.1.0.dev5.dist-info/top_level.txt
zone_hub-0.1.0.dev5.dist-info/RECORD
